{"url": "https://manassaloi.com/2024/05/15/thinking-lately.html", "title": "I have been thinking | Manas J. Saloi", "meta_description": "Mid April: I was down 3.2L INR (net) in Poker. I was up 40K mid January. So 3.6L down from peak. In 3 months.", "content": "I have been thinking | Manas J. Saloi Mid April: I was down 3.2L INR (net) in Poker. I was up 40K mid January. So 3.6L down from peak. In 3 months. Now I am up ~5.2L in 1 month. Positive 3L for the year. Have I become a dramatically better poker player in a month’s time? How much of my fall was due to luck / variance? How much of my bounce comes from skill? I have done the same job for the last few years. In my head, at least. I was HOP, now I have the fancy title of VP. Have I really learnt anything new in the last year and contributed dramatically more, or was I rewarded for staying put, for being in the right place at the right time? How do we know if we are really good at what we do? How do we not mistake luck for skill? How do we know if we are making better decisions than we did before? The hedonic treadmill is real. The joy of a pay rise lasts for a maximum of 3 days. After that you have the feeling that you should have got more. The previous year’s ambition turns into today’s standard. I was talking to a friend who works in a tier 1 global startup. He told me that being a public company VP is a good achievement, but my financial outcome has been the same as a first time PM who joined FANG a few years ago. Am I playing at the highest level? Should I be satisfied? Or should I strive for more? I was hanging out with another friend. He told me that he became much more humble in life when he found out that his brother-in-law makes 2/3 million a year because he has found some offline arbitrage opportunity, whereas this amount is the best possible outcome for my friend as an early hire at his startup. I have played poker with amazing players in the last few years, including someone who was #1 in online tournament poker in India. But winning no longer makes me happy. Even if I go on a heater and win a few lakhs, it does not change my net worth. When I lose, I feel like shit though. I ask if I really belong here. Who likes to lose anyway? I used to crush everyone in Fifa. Then I deleted Fifa because I had 3 consecutive losing sessions. Just 3. It is all that took. Poker is a crazy zero-sum endeavour. It is just a bunch of friends sitting down with each other to take each other’s money. If you asked someone if they would give you 70K (monthly rent of a 3bhk), they would of course say no. But they would 4bet jam with 27o just for the meme. Seeing people make such sub-optimal decisions is crazy. The early hires want to be founders. The VC backed founder wants to be a bootstrapper. Burnt out exec wants a sabbatical. The world wants the PM to become a ‘craftsman’. There is no end to it, but everyone is in pursuit of some end point where they will have the feeling that they have done it. Update: I lost 3L in 3 sessions. So I have given up all the gains for this year.", "html": "<!DOCTYPE html>\n<html lang=\"en\"><head>\n  <meta charset=\"utf-8\">\n  <meta http-equiv=\"X-UA-Compatible\" content=\"IE=edge\">\n  <meta name=\"viewport\" content=\"width=device-width, initial-scale=1\"><!-- Begin Jekyll SEO tag v2.8.0 -->\n<title>I have been thinking | Manas J. Saloi</title>\n<meta name=\"generator\" content=\"Jekyll v3.10.0\" />\n<meta property=\"og:title\" content=\"I have been thinking\" />\n<meta property=\"og:locale\" content=\"en_US\" />\n<meta name=\"description\" content=\"Mid April: I was down 3.2L INR (net) in Poker. I was up 40K mid January. So 3.6L down from peak. In 3 months.\" />\n<meta property=\"og:description\" content=\"Mid April: I was down 3.2L INR (net) in Poker. I was up 40K mid January. So 3.6L down from peak. In 3 months.\" />\n<link rel=\"canonical\" href=\"/2024/05/15/thinking-lately.html\" />\n<meta property=\"og:url\" content=\"/2024/05/15/thinking-lately.html\" />\n<meta property=\"og:site_name\" content=\"Manas J. Saloi\" />\n<meta property=\"og:image\" content=\"https://manassaloi.com/assets/img/manas.png\" />\n<meta property=\"og:type\" content=\"article\" />\n<meta property=\"article:published_time\" content=\"2024-05-15T00:00:00+00:00\" />\n<meta name=\"twitter:card\" content=\"summary_large_image\" />\n<meta property=\"twitter:image\" content=\"https://manassaloi.com/assets/img/manas.png\" />\n<meta property=\"twitter:title\" content=\"I have been thinking\" />\n<meta name=\"twitter:site\" content=\"@manas_saloi\" />\n<script type=\"application/ld+json\">\n{\"@context\":\"https://schema.org\",\"@type\":\"BlogPosting\",\"dateModified\":\"2024-05-15T00:00:00+00:00\",\"datePublished\":\"2024-05-15T00:00:00+00:00\",\"description\":\"Mid April: I was down 3.2L INR (net) in Poker. I was up 40K mid January. So 3.6L down from peak. In 3 months.\",\"headline\":\"I have been thinking\",\"image\":\"https://manassaloi.com/assets/img/manas.png\",\"mainEntityOfPage\":{\"@type\":\"WebPage\",\"@id\":\"/2024/05/15/thinking-lately.html\"},\"url\":\"/2024/05/15/thinking-lately.html\"}</script>\n<!-- End Jekyll SEO tag -->\n<link rel=\"stylesheet\" href=\"/assets/css/style.css\">\n  <link rel=\"shortcut icon\" type=\"image/png\" href=\"/assets/favicon.png\"><link type=\"application/atom+xml\" rel=\"alternate\" href=\"/feed.xml\" title=\"Manas J. Saloi\" /><script>\n    // Immediately set the theme before the page renders\n    (function() {\n      const savedTheme = localStorage.getItem('theme') || 'light';\n      document.documentElement.setAttribute('data-theme', savedTheme);\n      document.body.style.backgroundColor = savedTheme === 'dark' ? '#1a1a1a' : '#fdfdfd';\n      document.body.style.color = savedTheme === 'dark' ? '#f5f5f5' : '#111';\n    })();\n  </script>\n  <script src=\"/assets/js/theme-switcher.js\" defer></script>\n</head>\n<body><header class=\"site-header\">\n  <div class=\"wrapper\"><a class=\"site-title\" rel=\"author\" href=\"/\">Manas J. Saloi</a><nav class=\"site-nav\">\n        <input type=\"checkbox\" id=\"nav-trigger\" class=\"nav-trigger\" />\n        <label for=\"nav-trigger\">\n          <span class=\"menu-icon\">\n            <svg viewBox=\"0 0 18 15\" width=\"18px\" height=\"15px\">\n              <path d=\"M18,1.484c0,0.82-0.665,1.484-1.484,1.484H1.484C0.665,2.969,0,2.304,0,1.484l0,0C0,0.665,0.665,0,1.484,0 h15.032C17.335,0,18,0.665,18,1.484L18,1.484z M18,7.516C18,8.335,17.335,9,16.516,9H1.484C0.665,9,0,8.335,0,7.516l0,0 c0-0.82,0.665-1.484,1.484-1.484h15.032C17.335,6.031,18,6.696,18,7.516L18,7.516z M18,13.516C18,14.335,17.335,15,16.516,15H1.484 C0.665,15,0,14.335,0,13.516l0,0c0-0.82,0.665-1.483,1.484-1.483h15.032C17.335,12.031,18,12.695,18,13.516L18,13.516z\"/>\n            </svg>\n          </span>\n        </label>\n\n        <div class=\"trigger\"><a class=\"page-link\" href=\"/posts/\">Blog</a><a class=\"page-link\" href=\"/bookshelf/\">Bookshelf</a><a class=\"page-link\" href=\"/booksummaries/\">Summaries</a><a class=\"page-link\" href=\"/links/\">Links</a><a class=\"page-link\" href=\"/proofofwork/\">POW</a><a class=\"page-link\" href=\"/usesthis/\">Uses This</a></div>\n      </nav><div class=\"theme-switcher\">\n      <button class=\"theme-switcher__button\" onclick=\"toggleTheme()\" aria-label=\"Toggle theme\" title=\"Toggle dark/light mode\">\n        <span class=\"theme-switcher__icon theme-switcher__icon--light\">☀️</span>\n        <span class=\"theme-switcher__icon theme-switcher__icon--dark\">🌙</span>\n      </button>\n    </div>\n  </div>\n</header>\n<main class=\"page-content\" aria-label=\"Content\">\n      <div class=\"wrapper\">\n        <div class=\"letter-container\">\n  <div class=\"letter-paper\">\n    <article class=\"post h-entry\" itemscope itemtype=\"http://schema.org/BlogPosting\">\n\n      <header class=\"post-header\">\n        <h1 class=\"post-title p-name\" itemprop=\"name headline\">I have been thinking</h1>\n        <p class=\"post-meta\">\n          <time class=\"dt-published\" datetime=\"2024-05-15T00:00:00+00:00\" itemprop=\"datePublished\">May 15, 2024\n          </time></p>\n      </header>\n\n      <div class=\"post-content e-content\" itemprop=\"articleBody\">\n        <p>Mid April: I was down 3.2L INR (net) in Poker. I was up 40K mid January. So 3.6L down from peak. In 3 months.</p>\n\n<p>Now I am up ~5.2L in 1 month. Positive 3L for the year. Have I become a dramatically better poker player in a month’s time? How much of my fall was due to luck / variance? How much of my bounce comes from skill?</p>\n\n<p>I have done the same job for the last few years. In my head, at least. I was HOP, now I have the fancy title of VP. Have I really learnt anything new in the last year and contributed dramatically more, or was I rewarded for staying put, for being in the right place at the right time?</p>\n\n<p>How do we know if we are really good at what we do? How do we not mistake luck for skill? How do we know if we are making better decisions than we did before?</p>\n\n<p>The hedonic treadmill is real. The joy of a pay rise lasts for a maximum of 3 days. After that you have the feeling that you should have got more. The previous year’s ambition turns into today’s standard.</p>\n\n<p>I was talking to a friend who works in a tier 1 global startup. He told me that being a public company VP is a good achievement, but my financial outcome has been the same as a first time PM who joined FANG a few years ago.</p>\n\n<p>Am I playing at the highest level? Should I be satisfied? Or should I strive for more?</p>\n\n<p>I was hanging out with another friend. He told me that he became much more humble in life when he found out that his brother-in-law makes 2/3 million a year because he has found some offline arbitrage opportunity, whereas this amount is the best possible outcome for my friend as an early hire at his startup.</p>\n\n<p>I have played poker with amazing players in the last few years, including someone who was #1 in online tournament poker in India. But winning no longer makes me happy. Even if I go on a heater and win a few lakhs, it does not change my net worth. When I lose, I feel like shit though. I ask if I really belong here. Who likes to lose anyway? I used to crush everyone in Fifa. Then I deleted Fifa because I had 3 consecutive losing sessions. Just 3. It is all that took.</p>\n\n<p>Poker is a crazy zero-sum endeavour. It is just a bunch of friends sitting down with each other to take each other’s money. If you asked someone if they would give you 70K (monthly rent of a 3bhk), they would of course say no. But they would 4bet jam with 27o just for the meme. Seeing people make such sub-optimal decisions is crazy.</p>\n\n<p>The early hires want to be founders. The VC backed founder wants to be a bootstrapper. Burnt out exec wants a sabbatical. The world wants the PM to become a ‘craftsman’.</p>\n\n<p>There is no end to it, but everyone is in pursuit of some end point where they will have the feeling that they have done it.</p>\n\n<p>Update: I lost 3L in 3 sessions. So I have given up all the gains for this year.</p>\n\n      </div><a class=\"u-url\" href=\"/2024/05/15/thinking-lately.html\" hidden></a>\n    </article>\n  </div>\n</div>\n\n      </div>\n    </main><footer class=\"site-footer h-card\">\n  <data class=\"u-url\" href=\"/\"></data>\n\n  <div class=\"wrapper\">\n\n    <div class=\"footer-col-wrapper\">\n      <div class=\"footer-col one-half\">\n      <p class=\"footer-heading\"> Powered by <a href=\"https://jekyllrb.com\">Jekyll</a> and <a href=\"https://github.com/jekyll/minima\">Minima.</a> © Manas J Saloi.</p>\n\n      </div>\n      <div class=\"footer-col one-half\" style=\"text-align: right;\">\n       <h4></h4>\n      </div>\n    </div>\n\n  </div>\n\n</footer>\n</body>\n\n  <link href=\"https://fonts.googleapis.com/css2?family=Source+Sans+Pro:ital,wght@0,400;0,700;1,400&display=swap\" rel=\"stylesheet\">\n\n</html>\n", "crawl_time": 1751205259.334888}